[
  {"method":"Page.lifecycleEvent","params":{"frameId":"E238CD07DCE50A19F2D32BA4459B3546","loaderId":"AA21E207F0B38C9643267D2BB49B66C2","name":"commit","timestamp":14026.909789},"sessionId":"B12D271AD6E9B7F564EC1EE94D1DB8A2"},
  {"method":"Page.lifecycleEvent","params":{"frameId":"E238CD07DCE50A19F2D32BA4459B3546","loaderId":"AA21E207F0B38C9643267D2BB49B66C2","name":"DOMContentLoaded","timestamp":14026.909968},"sessionId":"B12D271AD6E9B7F564EC1EE94D1DB8A2"},
  {"method":"Page.lifecycleEvent","params":{"frameId":"E238CD07DCE50A19F2D32BA4459B3546","loaderId":"AA21E207F0B38C9643267D2BB49B66C2","name":"load","timestamp":14026.910524},"sessionId":"B12D271AD6E9B7F564EC1EE94D1DB8A2"},
  {"method":"Page.lifecycleEvent","params":{"frameId":"E238CD07DCE50A19F2D32BA4459B3546","loaderId":"AA21E207F0B38C9643267D2BB49B66C2","name":"networkAlmostIdle","timestamp":14026.911002},"sessionId":"B12D271AD6E9B7F564EC1EE94D1DB8A2"},
  {"method":"Page.lifecycleEvent","params":{"frameId":"E238CD07DCE50A19F2D32BA4459B3546","loaderId":"AA21E207F0B38C9643267D2BB49B66C2","name":"networkIdle","timestamp":14026.911002},"sessionId":"B12D271AD6E9B7F564EC1EE94D1DB8A2"},
  {"method":"Network.requestWillBeSent","params":{"requestId":"00067A54E4D57474C9DD15E683E7B32C","loaderId":"00067A54E4D57474C9DD15E683E7B32C","documentURL":"http://localhost:8081/employee-list.html","request":{"url":"http://localhost:8081/employee-list.html","method":"GET","headers":{"Upgrade-Insecure-Requests":"1","User-Agent":"Mozilla/5.0 (Linux; Android 11; moto g power (2022)) AppleWebKit/537.36 (KHTML, like Gecko) Chrome/109.0.0.0 Mobile Safari/537.36","sec-ch-ua":"\"Chromium\";v=\"109\", \"Google Chrome\";v=\"109\", \"Lighthouse\";v=\"10.0.0\"","sec-ch-ua-mobile":"?1","sec-ch-ua-platform":"\"Android\""},"mixedContentType":"none","initialPriority":"VeryHigh","referrerPolicy":"strict-origin-when-cross-origin","isSameSite":true},"timestamp":14027.062991,"wallTime":1677428158.11587,"initiator":{"type":"other"},"redirectHasExtraInfo":false,"type":"Document","frameId":"E238CD07DCE50A19F2D32BA4459B3546","hasUserGesture":false},"sessionId":"B12D271AD6E9B7F564EC1EE94D1DB8A2"},
  {"method":"Network.requestWillBeSentExtraInfo","params":{"requestId":"00067A54E4D57474C9DD15E683E7B32C","associatedCookies":[],"headers":{"Accept":"text/html,application/xhtml+xml,application/xml;q=0.9,image/avif,image/webp,image/apng,*/*;q=0.8,application/signed-exchange;v=b3;q=0.9","Accept-Encoding":"gzip, deflate, br","Accept-Language":"fr-FR,fr;q=0.9,en-US;q=0.8,en;q=0.7","Connection":"keep-alive","Host":"localhost:8081","Sec-Fetch-Dest":"document","Sec-Fetch-Mode":"navigate","Sec-Fetch-Site":"none","Sec-Fetch-User":"?1","Upgrade-Insecure-Requests":"1","User-Agent":"Mozilla/5.0 (Linux; Android 11; moto g power (2022)) AppleWebKit/537.36 (KHTML, like Gecko) Chrome/109.0.0.0 Mobile Safari/537.36","sec-ch-ua":"\"Chromium\";v=\"109\", \"Google Chrome\";v=\"109\", \"Lighthouse\";v=\"10.0.0\"","sec-ch-ua-mobile":"?1","sec-ch-ua-platform":"\"Android\""},"connectTiming":{"requestTime":14027.064582}},"sessionId":"B12D271AD6E9B7F564EC1EE94D1DB8A2"},
  {"method":"Network.responseReceivedExtraInfo","params":{"requestId":"00067A54E4D57474C9DD15E683E7B32C","blockedCookies":[],"headers":{"Connection":"keep-alive","Date":"Sun, 26 Feb 2023 16:15:58 GMT","Keep-Alive":"timeout=5","accept-ranges":"bytes","cache-control":"max-age=3600","content-length":"674","content-type":"text/html; charset=UTF-8","etag":"W/\"4999840-674-2023-02-12T14:25:47.268Z\"","last-modified":"Sun, 12 Feb 2023 14:25:47 GMT"},"resourceIPAddressSpace":"Local","statusCode":200,"headersText":"HTTP/1.1 200 OK\r\naccept-ranges: bytes\r\ncache-control: max-age=3600\r\nlast-modified: Sun, 12 Feb 2023 14:25:47 GMT\r\netag: W/\"4999840-674-2023-02-12T14:25:47.268Z\"\r\ncontent-length: 674\r\ncontent-type: text/html; charset=UTF-8\r\nDate: Sun, 26 Feb 2023 16:15:58 GMT\r\nConnection: keep-alive\r\nKeep-Alive: timeout=5\r\n\r\n"},"sessionId":"B12D271AD6E9B7F564EC1EE94D1DB8A2"},
  {"method":"Network.responseReceived","params":{"requestId":"00067A54E4D57474C9DD15E683E7B32C","loaderId":"00067A54E4D57474C9DD15E683E7B32C","timestamp":14027.069444,"type":"Document","response":{"url":"http://localhost:8081/employee-list.html","status":200,"statusText":"OK","headers":{"Connection":"keep-alive","Date":"Sun, 26 Feb 2023 16:15:58 GMT","Keep-Alive":"timeout=5","accept-ranges":"bytes","cache-control":"max-age=3600","content-length":"674","content-type":"text/html; charset=UTF-8","etag":"W/\"4999840-674-2023-02-12T14:25:47.268Z\"","last-modified":"Sun, 12 Feb 2023 14:25:47 GMT"},"mimeType":"text/html","connectionReused":true,"connectionId":47,"remoteIPAddress":"127.0.0.1","remotePort":8081,"fromDiskCache":false,"fromServiceWorker":false,"fromPrefetchCache":false,"encodedDataLength":309,"timing":{"requestTime":14027.064582,"proxyStart":-1,"proxyEnd":-1,"dnsStart":-1,"dnsEnd":-1,"connectStart":-1,"connectEnd":-1,"sslStart":-1,"sslEnd":-1,"workerStart":-1,"workerReady":-1,"workerFetchStart":-1,"workerRespondWithSettled":-1,"sendStart":0.762,"sendEnd":0.927,"pushStart":0,"pushEnd":0,"receiveHeadersEnd":2.947},"responseTime":1677428158120.173,"protocol":"http/1.1","alternateProtocolUsage":"unspecifiedReason","securityState":"secure"},"hasExtraInfo":true,"frameId":"E238CD07DCE50A19F2D32BA4459B3546"},"sessionId":"B12D271AD6E9B7F564EC1EE94D1DB8A2"},
  {"method":"Page.frameStartedLoading","params":{"frameId":"E238CD07DCE50A19F2D32BA4459B3546"},"sessionId":"B12D271AD6E9B7F564EC1EE94D1DB8A2"},
  {"method":"Page.lifecycleEvent","params":{"frameId":"E238CD07DCE50A19F2D32BA4459B3546","loaderId":"00067A54E4D57474C9DD15E683E7B32C","name":"init","timestamp":14027.073794},"sessionId":"B12D271AD6E9B7F564EC1EE94D1DB8A2"},
  {"method":"Network.requestWillBeSentExtraInfo","params":{"requestId":"214053.5","associatedCookies":[],"headers":{"Accept":"*/*","Accept-Encoding":"gzip, deflate, br","Accept-Language":"fr-FR,fr;q=0.9,en-US;q=0.8,en;q=0.7","Connection":"keep-alive","Host":"localhost:8081","Referer":"http://localhost:8081/employee-list.html","Sec-Fetch-Dest":"script","Sec-Fetch-Mode":"no-cors","Sec-Fetch-Site":"same-origin","User-Agent":"Mozilla/5.0 (Linux; Android 11; moto g power (2022)) AppleWebKit/537.36 (KHTML, like Gecko) Chrome/109.0.0.0 Mobile Safari/537.36","sec-ch-ua":"\"Chromium\";v=\"109\", \"Google Chrome\";v=\"109\", \"Lighthouse\";v=\"10.0.0\"","sec-ch-ua-mobile":"?1","sec-ch-ua-platform":"\"Android\""},"connectTiming":{"requestTime":14027.080975},"clientSecurityState":{"initiatorIsSecureContext":true,"initiatorIPAddressSpace":"Local","privateNetworkRequestPolicy":"PreflightWarn"}},"sessionId":"B12D271AD6E9B7F564EC1EE94D1DB8A2"},
  {"method":"Network.requestWillBeSentExtraInfo","params":{"requestId":"214053.6","associatedCookies":[],"headers":{"Accept":"text/css,*/*;q=0.1","Accept-Encoding":"gzip, deflate, br","Accept-Language":"fr-FR,fr;q=0.9,en-US;q=0.8,en;q=0.7","Connection":"keep-alive","Host":"localhost:8081","Referer":"http://localhost:8081/employee-list.html","Sec-Fetch-Dest":"style","Sec-Fetch-Mode":"no-cors","Sec-Fetch-Site":"same-origin","User-Agent":"Mozilla/5.0 (Linux; Android 11; moto g power (2022)) AppleWebKit/537.36 (KHTML, like Gecko) Chrome/109.0.0.0 Mobile Safari/537.36","sec-ch-ua":"\"Chromium\";v=\"109\", \"Google Chrome\";v=\"109\", \"Lighthouse\";v=\"10.0.0\"","sec-ch-ua-mobile":"?1","sec-ch-ua-platform":"\"Android\""},"connectTiming":{"requestTime":14027.081227},"clientSecurityState":{"initiatorIsSecureContext":true,"initiatorIPAddressSpace":"Local","privateNetworkRequestPolicy":"PreflightWarn"}},"sessionId":"B12D271AD6E9B7F564EC1EE94D1DB8A2"},
  {"method":"Runtime.executionContextsCleared","params":{},"sessionId":"B12D271AD6E9B7F564EC1EE94D1DB8A2"},
  {"method":"Page.frameNavigated","params":{"frame":{"id":"E238CD07DCE50A19F2D32BA4459B3546","loaderId":"00067A54E4D57474C9DD15E683E7B32C","url":"http://localhost:8081/employee-list.html","domainAndRegistry":"","securityOrigin":"http://localhost:8081","mimeType":"text/html","adFrameStatus":{"adFrameType":"none"},"secureContextType":"SecureLocalhost","crossOriginIsolatedContextType":"NotIsolated","gatedAPIFeatures":[]},"type":"Navigation"},"sessionId":"B12D271AD6E9B7F564EC1EE94D1DB8A2"},
  {"method":"Runtime.executionContextCreated","params":{"context":{"id":7,"origin":"http://localhost:8081","name":"","uniqueId":"-4440372599998593139.1562011375760334182","auxData":{"isDefault":true,"type":"default","frameId":"E238CD07DCE50A19F2D32BA4459B3546"}}},"sessionId":"B12D271AD6E9B7F564EC1EE94D1DB8A2"},
  {"method":"Network.dataReceived","params":{"requestId":"00067A54E4D57474C9DD15E683E7B32C","timestamp":14027.077858,"dataLength":674,"encodedDataLength":0},"sessionId":"B12D271AD6E9B7F564EC1EE94D1DB8A2"},
  {"method":"Network.requestWillBeSent","params":{"requestId":"214053.2","loaderId":"00067A54E4D57474C9DD15E683E7B32C","documentURL":"http://localhost:8081/employee-list.html","request":{"url":"https://ajax.googleapis.com/ajax/libs/jquery/3.5.1/jquery.min.js","method":"GET","headers":{"sec-ch-ua":"\"Chromium\";v=\"109\", \"Google Chrome\";v=\"109\", \"Lighthouse\";v=\"10.0.0\"","Referer":"http://localhost:8081/","sec-ch-ua-mobile":"?1","User-Agent":"Mozilla/5.0 (Linux; Android 11; moto g power (2022)) AppleWebKit/537.36 (KHTML, like Gecko) Chrome/109.0.0.0 Mobile Safari/537.36","sec-ch-ua-platform":"\"Android\""},"mixedContentType":"none","initialPriority":"High","referrerPolicy":"strict-origin-when-cross-origin","isSameSite":false},"timestamp":14027.07832,"wallTime":1677428158.1312,"initiator":{"type":"parser","url":"http://localhost:8081/employee-list.html","lineNumber":3,"columnNumber":83},"redirectHasExtraInfo":false,"type":"Script","frameId":"E238CD07DCE50A19F2D32BA4459B3546","hasUserGesture":false},"sessionId":"B12D271AD6E9B7F564EC1EE94D1DB8A2"},
  {"method":"Network.requestWillBeSent","params":{"requestId":"214053.3","loaderId":"00067A54E4D57474C9DD15E683E7B32C","documentURL":"http://localhost:8081/employee-list.html","request":{"url":"https://cdn.datatables.net/1.10.21/js/jquery.dataTables.min.js","method":"GET","headers":{"sec-ch-ua":"\"Chromium\";v=\"109\", \"Google Chrome\";v=\"109\", \"Lighthouse\";v=\"10.0.0\"","Referer":"http://localhost:8081/","sec-ch-ua-mobile":"?1","User-Agent":"Mozilla/5.0 (Linux; Android 11; moto g power (2022)) AppleWebKit/537.36 (KHTML, like Gecko) Chrome/109.0.0.0 Mobile Safari/537.36","sec-ch-ua-platform":"\"Android\""},"mixedContentType":"none","initialPriority":"High","referrerPolicy":"strict-origin-when-cross-origin","isSameSite":false},"timestamp":14027.078854,"wallTime":1677428158.131698,"initiator":{"type":"parser","url":"http://localhost:8081/employee-list.html","lineNumber":4,"columnNumber":81},"redirectHasExtraInfo":false,"type":"Script","frameId":"E238CD07DCE50A19F2D32BA4459B3546","hasUserGesture":false},"sessionId":"B12D271AD6E9B7F564EC1EE94D1DB8A2"},
  {"method":"Network.requestWillBeSent","params":{"requestId":"214053.4","loaderId":"00067A54E4D57474C9DD15E683E7B32C","documentURL":"http://localhost:8081/employee-list.html","request":{"url":"https://cdn.datatables.net/1.10.21/css/jquery.dataTables.min.css","method":"GET","headers":{"sec-ch-ua":"\"Chromium\";v=\"109\", \"Google Chrome\";v=\"109\", \"Lighthouse\";v=\"10.0.0\"","Referer":"http://localhost:8081/","sec-ch-ua-mobile":"?1","User-Agent":"Mozilla/5.0 (Linux; Android 11; moto g power (2022)) AppleWebKit/537.36 (KHTML, like Gecko) Chrome/109.0.0.0 Mobile Safari/537.36","sec-ch-ua-platform":"\"Android\""},"mixedContentType":"none","initialPriority":"VeryHigh","referrerPolicy":"strict-origin-when-cross-origin","isSameSite":false},"timestamp":14027.079274,"wallTime":1677428158.132133,"initiator":{"type":"parser","url":"http://localhost:8081/employee-list.html","lineNumber":8,"columnNumber":6},"redirectHasExtraInfo":false,"type":"Stylesheet","frameId":"E238CD07DCE50A19F2D32BA4459B3546","hasUserGesture":false},"sessionId":"B12D271AD6E9B7F564EC1EE94D1DB8A2"},
  {"method":"Network.requestWillBeSent","params":{"requestId":"214053.5","loaderId":"00067A54E4D57474C9DD15E683E7B32C","documentURL":"http://localhost:8081/employee-list.html","request":{"url":"http://localhost:8081/employee-list.js","method":"GET","headers":{"sec-ch-ua":"\"Chromium\";v=\"109\", \"Google Chrome\";v=\"109\", \"Lighthouse\";v=\"10.0.0\"","Referer":"http://localhost:8081/employee-list.html","sec-ch-ua-mobile":"?1","User-Agent":"Mozilla/5.0 (Linux; Android 11; moto g power (2022)) AppleWebKit/537.36 (KHTML, like Gecko) Chrome/109.0.0.0 Mobile Safari/537.36","sec-ch-ua-platform":"\"Android\""},"mixedContentType":"none","initialPriority":"High","referrerPolicy":"strict-origin-when-cross-origin","isSameSite":true},"timestamp":14027.079683,"wallTime":1677428158.132524,"initiator":{"type":"parser","url":"http://localhost:8081/employee-list.html","lineNumber":9,"columnNumber":35},"redirectHasExtraInfo":false,"type":"Script","frameId":"E238CD07DCE50A19F2D32BA4459B3546","hasUserGesture":false},"sessionId":"B12D271AD6E9B7F564EC1EE94D1DB8A2"},
  {"method":"Network.requestWillBeSent","params":{"requestId":"214053.6","loaderId":"00067A54E4D57474C9DD15E683E7B32C","documentURL":"http://localhost:8081/employee-list.html","request":{"url":"http://localhost:8081/app.css","method":"GET","headers":{"sec-ch-ua":"\"Chromium\";v=\"109\", \"Google Chrome\";v=\"109\", \"Lighthouse\";v=\"10.0.0\"","Referer":"http://localhost:8081/employee-list.html","sec-ch-ua-mobile":"?1","User-Agent":"Mozilla/5.0 (Linux; Android 11; moto g power (2022)) AppleWebKit/537.36 (KHTML, like Gecko) Chrome/109.0.0.0 Mobile Safari/537.36","sec-ch-ua-platform":"\"Android\""},"mixedContentType":"none","initialPriority":"VeryHigh","referrerPolicy":"strict-origin-when-cross-origin","isSameSite":true},"timestamp":14027.080076,"wallTime":1677428158.132939,"initiator":{"type":"parser","url":"http://localhost:8081/employee-list.html","lineNumber":10,"columnNumber":44},"redirectHasExtraInfo":false,"type":"Stylesheet","frameId":"E238CD07DCE50A19F2D32BA4459B3546","hasUserGesture":false},"sessionId":"B12D271AD6E9B7F564EC1EE94D1DB8A2"},
  {"method":"Runtime.executionContextCreated","params":{"context":{"id":8,"origin":"://","name":"__puppeteer_utility_world__","uniqueId":"-4443489532888097250.-2038337930784389294","auxData":{"isDefault":false,"type":"isolated","frameId":"E238CD07DCE50A19F2D32BA4459B3546"}}},"sessionId":"B12D271AD6E9B7F564EC1EE94D1DB8A2"},
  {"method":"Network.loadingFinished","params":{"requestId":"00067A54E4D57474C9DD15E683E7B32C","timestamp":14027.068819,"encodedDataLength":983,"shouldReportCorbBlocking":false},"sessionId":"B12D271AD6E9B7F564EC1EE94D1DB8A2"},
  {"method":"Network.responseReceivedExtraInfo","params":{"requestId":"214053.5","blockedCookies":[],"headers":{"Connection":"keep-alive","Date":"Sun, 26 Feb 2023 16:15:58 GMT","Keep-Alive":"timeout=5","accept-ranges":"bytes","cache-control":"max-age=3600","content-length":"664","content-type":"application/javascript; charset=UTF-8","etag":"W/\"4999877-664-2020-07-12T04:43:47.000Z\"","last-modified":"Sun, 12 Jul 2020 04:43:47 GMT"},"resourceIPAddressSpace":"Local","statusCode":200,"headersText":"HTTP/1.1 200 OK\r\naccept-ranges: bytes\r\ncache-control: max-age=3600\r\nlast-modified: Sun, 12 Jul 2020 04:43:47 GMT\r\netag: W/\"4999877-664-2020-07-12T04:43:47.000Z\"\r\ncontent-length: 664\r\ncontent-type: application/javascript; charset=UTF-8\r\nDate: Sun, 26 Feb 2023 16:15:58 GMT\r\nConnection: keep-alive\r\nKeep-Alive: timeout=5\r\n\r\n"},"sessionId":"B12D271AD6E9B7F564EC1EE94D1DB8A2"},
  {"method":"Network.responseReceivedExtraInfo","params":{"requestId":"214053.6","blockedCookies":[],"headers":{"Connection":"keep-alive","Date":"Sun, 26 Feb 2023 16:15:58 GMT","Keep-Alive":"timeout=5","accept-ranges":"bytes","cache-control":"max-age=3600","content-length":"315","content-type":"text/css; charset=UTF-8","etag":"W/\"4999719-315-2020-07-12T04:43:47.000Z\"","last-modified":"Sun, 12 Jul 2020 04:43:47 GMT"},"resourceIPAddressSpace":"Local","statusCode":200,"headersText":"HTTP/1.1 200 OK\r\naccept-ranges: bytes\r\ncache-control: max-age=3600\r\nlast-modified: Sun, 12 Jul 2020 04:43:47 GMT\r\netag: W/\"4999719-315-2020-07-12T04:43:47.000Z\"\r\ncontent-length: 315\r\ncontent-type: text/css; charset=UTF-8\r\nDate: Sun, 26 Feb 2023 16:15:58 GMT\r\nConnection: keep-alive\r\nKeep-Alive: timeout=5\r\n\r\n"},"sessionId":"B12D271AD6E9B7F564EC1EE94D1DB8A2"},
  {"method":"Network.responseReceived","params":{"requestId":"214053.5","loaderId":"00067A54E4D57474C9DD15E683E7B32C","timestamp":14027.089586,"type":"Script","response":{"url":"http://localhost:8081/employee-list.js","status":200,"statusText":"OK","headers":{"Date":"Sun, 26 Feb 2023 16:15:58 GMT","last-modified":"Sun, 12 Jul 2020 04:43:47 GMT","etag":"W/\"4999877-664-2020-07-12T04:43:47.000Z\"","content-type":"application/javascript; charset=UTF-8","cache-control":"max-age=3600","Connection":"keep-alive","accept-ranges":"bytes","Keep-Alive":"timeout=5","content-length":"664"},"mimeType":"application/javascript","connectionReused":true,"connectionId":47,"remoteIPAddress":"127.0.0.1","remotePort":8081,"fromDiskCache":false,"fromServiceWorker":false,"fromPrefetchCache":false,"encodedDataLength":322,"timing":{"requestTime":14027.080975,"proxyStart":-1,"proxyEnd":-1,"dnsStart":-1,"dnsEnd":-1,"connectStart":-1,"connectEnd":-1,"sslStart":-1,"sslEnd":-1,"workerStart":-1,"workerReady":-1,"workerFetchStart":-1,"workerRespondWithSettled":-1,"sendStart":0.893,"sendEnd":0.964,"pushStart":0,"pushEnd":0,"receiveHeadersEnd":7.424},"responseTime":1677428158141.06,"protocol":"http/1.1","alternateProtocolUsage":"unspecifiedReason","securityState":"secure"},"hasExtraInfo":true,"frameId":"E238CD07DCE50A19F2D32BA4459B3546"},"sessionId":"B12D271AD6E9B7F564EC1EE94D1DB8A2"},
  {"method":"Network.responseReceived","params":{"requestId":"214053.6","loaderId":"00067A54E4D57474C9DD15E683E7B32C","timestamp":14027.09065,"type":"Stylesheet","response":{"url":"http://localhost:8081/app.css","status":200,"statusText":"OK","headers":{"Date":"Sun, 26 Feb 2023 16:15:58 GMT","last-modified":"Sun, 12 Jul 2020 04:43:47 GMT","etag":"W/\"4999719-315-2020-07-12T04:43:47.000Z\"","content-type":"text/css; charset=UTF-8","cache-control":"max-age=3600","Connection":"keep-alive","accept-ranges":"bytes","Keep-Alive":"timeout=5","content-length":"315"},"mimeType":"text/css","connectionReused":true,"connectionId":57,"remoteIPAddress":"127.0.0.1","remotePort":8081,"fromDiskCache":false,"fromServiceWorker":false,"fromPrefetchCache":false,"encodedDataLength":308,"timing":{"requestTime":14027.081227,"proxyStart":-1,"proxyEnd":-1,"dnsStart":-1,"dnsEnd":-1,"connectStart":-1,"connectEnd":-1,"sslStart":-1,"sslEnd":-1,"workerStart":-1,"workerReady":-1,"workerFetchStart":-1,"workerRespondWithSettled":-1,"sendStart":0.736,"sendEnd":0.792,"pushStart":0,"pushEnd":0,"receiveHeadersEnd":8.165},"responseTime":1677428158142.11,"protocol":"http/1.1","alternateProtocolUsage":"unspecifiedReason","securityState":"secure"},"hasExtraInfo":true,"frameId":"E238CD07DCE50A19F2D32BA4459B3546"},"sessionId":"B12D271AD6E9B7F564EC1EE94D1DB8A2"},
  {"method":"Network.dataReceived","params":{"requestId":"214053.6","timestamp":14027.090735,"dataLength":315,"encodedDataLength":0},"sessionId":"B12D271AD6E9B7F564EC1EE94D1DB8A2"},
  {"method":"Network.dataReceived","params":{"requestId":"214053.5","timestamp":14027.090871,"dataLength":664,"encodedDataLength":664},"sessionId":"B12D271AD6E9B7F564EC1EE94D1DB8A2"},
  {"method":"Network.dataReceived","params":{"requestId":"214053.6","timestamp":14027.091525,"dataLength":0,"encodedDataLength":315},"sessionId":"B12D271AD6E9B7F564EC1EE94D1DB8A2"},
  {"method":"Network.loadingFinished","params":{"requestId":"214053.6","timestamp":14027.090807,"encodedDataLength":623,"shouldReportCorbBlocking":false},"sessionId":"B12D271AD6E9B7F564EC1EE94D1DB8A2"},
  {"method":"Network.loadingFinished","params":{"requestId":"214053.5","timestamp":14027.090562,"encodedDataLength":986,"shouldReportCorbBlocking":false},"sessionId":"B12D271AD6E9B7F564EC1EE94D1DB8A2"},
  {"method":"Network.requestWillBeSentExtraInfo","params":{"requestId":"214053.2","associatedCookies":[],"headers":{":authority":"ajax.googleapis.com",":method":"GET",":path":"/ajax/libs/jquery/3.5.1/jquery.min.js",":scheme":"https","accept":"*/*","accept-encoding":"gzip, deflate, br","accept-language":"fr-FR,fr;q=0.9,en-US;q=0.8,en;q=0.7","referer":"http://localhost:8081/","sec-ch-ua":"\"Chromium\";v=\"109\", \"Google Chrome\";v=\"109\", \"Lighthouse\";v=\"10.0.0\"","sec-ch-ua-mobile":"?1","sec-ch-ua-platform":"\"Android\"","sec-fetch-dest":"script","sec-fetch-mode":"no-cors","sec-fetch-site":"cross-site","user-agent":"Mozilla/5.0 (Linux; Android 11; moto g power (2022)) AppleWebKit/537.36 (KHTML, like Gecko) Chrome/109.0.0.0 Mobile Safari/537.36","x-client-data":"CJndygE="},"connectTiming":{"requestTime":14027.079897},"clientSecurityState":{"initiatorIsSecureContext":true,"initiatorIPAddressSpace":"Local","privateNetworkRequestPolicy":"PreflightWarn"}},"sessionId":"B12D271AD6E9B7F564EC1EE94D1DB8A2"},
  {"method":"Network.responseReceivedExtraInfo","params":{"requestId":"214053.2","blockedCookies":[],"headers":{"accept-ranges":"bytes","access-control-allow-origin":"*","age":"291677","alt-svc":"h3=\":443\"; ma=2592000,h3-29=\":443\"; ma=2592000","cache-control":"public, max-age=31536000, stale-while-revalidate=2592000","content-encoding":"gzip","content-length":"31021","content-security-policy-report-only":"require-trusted-types-for 'script'; report-uri https://csp.withgoogle.com/csp/hosted-libraries-pushers","content-type":"text/javascript; charset=UTF-8","cross-origin-opener-policy":"same-origin; report-to=\"hosted-libraries-pushers\"","cross-origin-resource-policy":"cross-origin","date":"Thu, 23 Feb 2023 07:14:41 GMT","expires":"Fri, 23 Feb 2024 07:14:41 GMT","last-modified":"Fri, 08 May 2020 07:05:03 GMT","report-to":"{\"group\":\"hosted-libraries-pushers\",\"max_age\":2592000,\"endpoints\":[{\"url\":\"https://csp.withgoogle.com/csp/report-to/hosted-libraries-pushers\"}]}","server":"sffe","timing-allow-origin":"*","vary":"Accept-Encoding","x-content-type-options":"nosniff","x-xss-protection":"0"},"resourceIPAddressSpace":"Public","statusCode":200},"sessionId":"B12D271AD6E9B7F564EC1EE94D1DB8A2"},
  {"method":"Network.requestWillBeSentExtraInfo","params":{"requestId":"214053.4","associatedCookies":[],"headers":{":authority":"cdn.datatables.net",":method":"GET",":path":"/1.10.21/css/jquery.dataTables.min.css",":scheme":"https","accept":"text/css,*/*;q=0.1","accept-encoding":"gzip, deflate, br","accept-language":"fr-FR,fr;q=0.9,en-US;q=0.8,en;q=0.7","referer":"http://localhost:8081/","sec-ch-ua":"\"Chromium\";v=\"109\", \"Google Chrome\";v=\"109\", \"Lighthouse\";v=\"10.0.0\"","sec-ch-ua-mobile":"?1","sec-ch-ua-platform":"\"Android\"","sec-fetch-dest":"style","sec-fetch-mode":"no-cors","sec-fetch-site":"cross-site","user-agent":"Mozilla/5.0 (Linux; Android 11; moto g power (2022)) AppleWebKit/537.36 (KHTML, like Gecko) Chrome/109.0.0.0 Mobile Safari/537.36"},"connectTiming":{"requestTime":14027.080777},"clientSecurityState":{"initiatorIsSecureContext":true,"initiatorIPAddressSpace":"Local","privateNetworkRequestPolicy":"PreflightWarn"}},"sessionId":"B12D271AD6E9B7F564EC1EE94D1DB8A2"},
  {"method":"Network.requestWillBeSentExtraInfo","params":{"requestId":"214053.3","associatedCookies":[],"headers":{":authority":"cdn.datatables.net",":method":"GET",":path":"/1.10.21/js/jquery.dataTables.min.js",":scheme":"https","accept":"*/*","accept-encoding":"gzip, deflate, br","accept-language":"fr-FR,fr;q=0.9,en-US;q=0.8,en;q=0.7","referer":"http://localhost:8081/","sec-ch-ua":"\"Chromium\";v=\"109\", \"Google Chrome\";v=\"109\", \"Lighthouse\";v=\"10.0.0\"","sec-ch-ua-mobile":"?1","sec-ch-ua-platform":"\"Android\"","sec-fetch-dest":"script","sec-fetch-mode":"no-cors","sec-fetch-site":"cross-site","user-agent":"Mozilla/5.0 (Linux; Android 11; moto g power (2022)) AppleWebKit/537.36 (KHTML, like Gecko) Chrome/109.0.0.0 Mobile Safari/537.36"},"connectTiming":{"requestTime":14027.080434},"clientSecurityState":{"initiatorIsSecureContext":true,"initiatorIPAddressSpace":"Local","privateNetworkRequestPolicy":"PreflightWarn"}},"sessionId":"B12D271AD6E9B7F564EC1EE94D1DB8A2"},
  {"method":"Network.responseReceived","params":{"requestId":"214053.2","loaderId":"00067A54E4D57474C9DD15E683E7B32C","timestamp":14027.251174,"type":"Script","response":{"url":"https://ajax.googleapis.com/ajax/libs/jquery/3.5.1/jquery.min.js","status":200,"statusText":"","headers":{"date":"Thu, 23 Feb 2023 07:14:41 GMT","content-encoding":"gzip","x-content-type-options":"nosniff","age":"291677","content-security-policy-report-only":"require-trusted-types-for 'script'; report-uri https://csp.withgoogle.com/csp/hosted-libraries-pushers","cross-origin-resource-policy":"cross-origin","alt-svc":"h3=\":443\"; ma=2592000,h3-29=\":443\"; ma=2592000","content-length":"31021","x-xss-protection":"0","last-modified":"Fri, 08 May 2020 07:05:03 GMT","server":"sffe","cross-origin-opener-policy":"same-origin; report-to=\"hosted-libraries-pushers\"","vary":"Accept-Encoding","report-to":"{\"group\":\"hosted-libraries-pushers\",\"max_age\":2592000,\"endpoints\":[{\"url\":\"https://csp.withgoogle.com/csp/report-to/hosted-libraries-pushers\"}]}","content-type":"text/javascript; charset=UTF-8","access-control-allow-origin":"*","cache-control":"public, max-age=31536000, stale-while-revalidate=2592000","accept-ranges":"bytes","timing-allow-origin":"*","expires":"Fri, 23 Feb 2024 07:14:41 GMT"},"mimeType":"text/javascript","connectionReused":false,"connectionId":76,"remoteIPAddress":"[2a00:1450:400a:808::200a]","remotePort":443,"fromDiskCache":false,"fromServiceWorker":false,"fromPrefetchCache":false,"encodedDataLength":614,"timing":{"requestTime":14027.079897,"proxyStart":-1,"proxyEnd":-1,"dnsStart":0.211,"dnsEnd":1.642,"connectStart":1.642,"connectEnd":145.973,"sslStart":12.082,"sslEnd":145.963,"workerStart":-1,"workerReady":-1,"workerFetchStart":-1,"workerRespondWithSettled":-1,"sendStart":146.193,"sendEnd":146.3,"pushStart":0,"pushEnd":0,"receiveHeadersEnd":159.389},"responseTime":1677428158291.763,"protocol":"h2","alternateProtocolUsage":"unspecifiedReason","securityState":"secure","securityDetails":{"protocol":"TLS 1.3","keyExchange":"","keyExchangeGroup":"X25519","cipher":"AES_128_GCM","certificateId":0,"subjectName":"upload.video.google.com","sanList":["upload.video.google.com","*.clients.google.com","*.docs.google.com","*.drive.google.com","*.gdata.youtube.com","*.googleapis.com","*.photos.google.com","*.youtube-3rd-party.com","upload.google.com","*.upload.google.com","upload.youtube.com","*.upload.youtube.com","uploads.stage.gdata.youtube.com","bg-call-donation.goog","bg-call-donation-alpha.goog","bg-call-donation-canary.goog","bg-call-donation-dev.goog"],"issuer":"GTS CA 1C3","validFrom":1675830961,"validTo":1683088560,"signedCertificateTimestampList":[{"status":"Verified","origin":"Embedded in certificate","logDescription":"Cloudflare 'Nimbus2023' Log","logId":"7A328C54D8B72DB620EA38E0521EE98416703213854D3BD22BC13A57A352EB52","timestamp":1675834563023,"hashAlgorithm":"SHA-256","signatureAlgorithm":"ECDSA","signatureData":"304402200FF0AEDC786916B83EA25CE4807B09B6838EBE9360B1C3A93EE61C3D36958AA8022036B70A34A5723C77C5911430719A9A0D37F2F02443B80395F7020CE87654488C"},{"status":"Verified","origin":"Embedded in certificate","logDescription":"Google 'Argon2023' log","logId":"E83ED0DA3EF5063532E75728BC896BC903D3CBD1116BECEB69E1777D6D06BD6E","timestamp":1675834562957,"hashAlgorithm":"SHA-256","signatureAlgorithm":"ECDSA","signatureData":"3046022100811B9A4D56EE4D0B6CB385BFCFA71EAE50A78D489FBD4821CB1CFBCB0293571E022100FBDE34FAE23246EABD687E8C4ADCAFCD31CADB28DDF167D762C8A692FDABE6EF"}],"certificateTransparencyCompliance":"unknown","serverSignatureAlgorithm":1027,"encryptedClientHello":false}},"hasExtraInfo":true,"frameId":"E238CD07DCE50A19F2D32BA4459B3546"},"sessionId":"B12D271AD6E9B7F564EC1EE94D1DB8A2"},
  {"method":"Network.dataReceived","params":{"requestId":"214053.2","timestamp":14027.251318,"dataLength":89476,"encodedDataLength":0},"sessionId":"B12D271AD6E9B7F564EC1EE94D1DB8A2"},
  {"method":"Network.dataReceived","params":{"requestId":"214053.2","timestamp":14027.258332,"dataLength":0,"encodedDataLength":31039},"sessionId":"B12D271AD6E9B7F564EC1EE94D1DB8A2"},
  {"method":"Network.loadingFinished","params":{"requestId":"214053.2","timestamp":14027.250772,"encodedDataLength":31653,"shouldReportCorbBlocking":false},"sessionId":"B12D271AD6E9B7F564EC1EE94D1DB8A2"},
  {"method":"Network.responseReceivedExtraInfo","params":{"requestId":"214053.4","blockedCookies":[],"headers":{"accept-ranges":"bytes","access-control-allow-headers":"origin, x-requested-with, content-type","access-control-allow-methods":"GET","access-control-allow-origin":"*","age":"2205954","cache-control":"max-age=31536000","cf-cache-status":"HIT","cf-ray":"79f9fb8569b73a3e-FRA","content-encoding":"gzip","content-length":"2107","content-type":"text/css; charset=utf-8","date":"Sun, 26 Feb 2023 16:15:58 GMT","etag":"\"15a00bc-3644-5ed32f45b3898-gzip\"","expires":"Thu, 01 Feb 2024 03:30:03 GMT","last-modified":"Fri, 11 Nov 2022 14:46:27 GMT","server":"cloudflare","vary":"Accept-Encoding,User-Agent","x-frame-options":"SAMEORIGIN"},"resourceIPAddressSpace":"Public","statusCode":200},"sessionId":"B12D271AD6E9B7F564EC1EE94D1DB8A2"},
  {"method":"Network.responseReceived","params":{"requestId":"214053.4","loaderId":"00067A54E4D57474C9DD15E683E7B32C","timestamp":14027.276949,"type":"Stylesheet","response":{"url":"https://cdn.datatables.net/1.10.21/css/jquery.dataTables.min.css","status":200,"statusText":"","headers":{"date":"Sun, 26 Feb 2023 16:15:58 GMT","content-encoding":"gzip","cf-cache-status":"HIT","age":"2205954","content-length":"2107","last-modified":"Fri, 11 Nov 2022 14:46:27 GMT","server":"cloudflare","etag":"\"15a00bc-3644-5ed32f45b3898-gzip\"","x-frame-options":"SAMEORIGIN","vary":"Accept-Encoding,User-Agent","content-type":"text/css; charset=utf-8","access-control-allow-origin":"*","access-control-allow-methods":"GET","cache-control":"max-age=31536000","accept-ranges":"bytes","cf-ray":"79f9fb8569b73a3e-FRA","access-control-allow-headers":"origin, x-requested-with, content-type","expires":"Thu, 01 Feb 2024 03:30:03 GMT"},"mimeType":"text/css","connectionReused":false,"connectionId":84,"remoteIPAddress":"[2606:4700:10::6816:325d]","remotePort":443,"fromDiskCache":false,"fromServiceWorker":false,"fromPrefetchCache":false,"encodedDataLength":340,"timing":{"requestTime":14027.080777,"proxyStart":-1,"proxyEnd":-1,"dnsStart":0.684,"dnsEnd":10.235,"connectStart":10.235,"connectEnd":165.81,"sslStart":27.715,"sslEnd":165.798,"workerStart":-1,"workerReady":-1,"workerFetchStart":-1,"workerRespondWithSettled":-1,"sendStart":166.84,"sendEnd":167.058,"pushStart":0,"pushEnd":0,"receiveHeadersEnd":194.26},"responseTime":1677428158327.622,"protocol":"h2","alternateProtocolUsage":"unspecifiedReason","securityState":"secure","securityDetails":{"protocol":"TLS 1.3","keyExchange":"","keyExchangeGroup":"X25519","cipher":"AES_128_GCM","certificateId":0,"subjectName":"sni.cloudflaressl.com","sanList":["datatables.net","*.datatables.net","sni.cloudflaressl.com"],"issuer":"Cloudflare Inc ECC CA-3","validFrom":1653696000,"validTo":1685318399,"signedCertificateTimestampList":[{"status":"Verified","origin":"Embedded in certificate","logDescription":"Google 'Xenon2023' log","logId":"ADF7BEFA7CFF10C88B9D3D9C1E3E186AB467295DCFB10C24CA858634EBDC828A","timestamp":1653702588059,"hashAlgorithm":"SHA-256","signatureAlgorithm":"ECDSA","signatureData":"30460221008A55E457978298E81C9EEA55768E3143D396559565BE638B7A1ADE0722B4416A022100FA744101E4AC45B8D4A3CA834AF9BEC4047E8D8816D51BCE297959DA55CE13CB"},{"status":"Verified","origin":"Embedded in certificate","logDescription":"DigiCert Yeti2023 Log","logId":"35CF191BBFB16C57BF0FAD4C6D42CBBBB627202651EA3FE12AEFA803C33BD64C","timestamp":1653702588020,"hashAlgorithm":"SHA-256","signatureAlgorithm":"ECDSA","signatureData":"3045022065B0396483E025C43DA4D5C0853F063A10AE86E72AEBC84ED73909C9701EC2BF022100AA5B9EA28ECC746B83697A8C26AA9F8D79EE04DCE1C4A74C21AC0362D3048894"},{"status":"Verified","origin":"Embedded in certificate","logDescription":"DigiCert Nessie2023 Log","logId":"B3737707E18450F86386D605A9DC11094A792DB1670C0B87DCF0030E7936A59A","timestamp":1653702588056,"hashAlgorithm":"SHA-256","signatureAlgorithm":"ECDSA","signatureData":"304402203FADD94F60E5060A766D686DF7EFCD4A89F15B8857CF0BFA5FD5430CABE8FD2B02200B134BF7EB64B66E4B593039780F04D133251E4C9C944E7E313A70D2AEF682FD"}],"certificateTransparencyCompliance":"unknown","serverSignatureAlgorithm":1027,"encryptedClientHello":false}},"hasExtraInfo":true,"frameId":"E238CD07DCE50A19F2D32BA4459B3546"},"sessionId":"B12D271AD6E9B7F564EC1EE94D1DB8A2"},
  {"method":"Network.dataReceived","params":{"requestId":"214053.4","timestamp":14027.27703,"dataLength":13892,"encodedDataLength":0},"sessionId":"B12D271AD6E9B7F564EC1EE94D1DB8A2"},
  {"method":"Network.loadingFinished","params":{"requestId":"214053.4","timestamp":14027.276496,"encodedDataLength":2465,"shouldReportCorbBlocking":false},"sessionId":"B12D271AD6E9B7F564EC1EE94D1DB8A2"},
  {"method":"Network.responseReceivedExtraInfo","params":{"requestId":"214053.3","blockedCookies":[],"headers":{"accept-ranges":"bytes","access-control-allow-headers":"origin, x-requested-with, content-type","access-control-allow-methods":"GET","access-control-allow-origin":"*","age":"2205954","cache-control":"max-age=31536000","cf-cache-status":"HIT","cf-ray":"79f9fb8569bb3a3e-FRA","content-encoding":"gzip","content-length":"29029","content-type":"application/javascript; charset=utf-8","date":"Sun, 26 Feb 2023 16:15:58 GMT","etag":"\"15a005e-14aa7-5ed32f45b7718-gzip\"","expires":"Thu, 01 Feb 2024 03:30:03 GMT","last-modified":"Fri, 11 Nov 2022 14:46:27 GMT","server":"cloudflare","vary":"Accept-Encoding,User-Agent","x-frame-options":"SAMEORIGIN"},"resourceIPAddressSpace":"Public","statusCode":200},"sessionId":"B12D271AD6E9B7F564EC1EE94D1DB8A2"},
  {"method":"Network.responseReceived","params":{"requestId":"214053.3","loaderId":"00067A54E4D57474C9DD15E683E7B32C","timestamp":14027.2818,"type":"Script","response":{"url":"https://cdn.datatables.net/1.10.21/js/jquery.dataTables.min.js","status":200,"statusText":"","headers":{"date":"Sun, 26 Feb 2023 16:15:58 GMT","content-encoding":"gzip","cf-cache-status":"HIT","age":"2205954","content-length":"29029","last-modified":"Fri, 11 Nov 2022 14:46:27 GMT","server":"cloudflare","etag":"\"15a005e-14aa7-5ed32f45b7718-gzip\"","x-frame-options":"SAMEORIGIN","vary":"Accept-Encoding,User-Agent","content-type":"application/javascript; charset=utf-8","access-control-allow-origin":"*","access-control-allow-methods":"GET","cache-control":"max-age=31536000","accept-ranges":"bytes","cf-ray":"79f9fb8569bb3a3e-FRA","access-control-allow-headers":"origin, x-requested-with, content-type","expires":"Thu, 01 Feb 2024 03:30:03 GMT"},"mimeType":"application/javascript","connectionReused":true,"connectionId":84,"remoteIPAddress":"[2606:4700:10::6816:325d]","remotePort":443,"fromDiskCache":false,"fromServiceWorker":false,"fromPrefetchCache":false,"encodedDataLength":104,"timing":{"requestTime":14027.080434,"proxyStart":-1,"proxyEnd":-1,"dnsStart":-1,"dnsEnd":-1,"connectStart":-1,"connectEnd":-1,"sslStart":-1,"sslEnd":-1,"workerStart":-1,"workerReady":-1,"workerFetchStart":-1,"workerRespondWithSettled":-1,"sendStart":167.263,"sendEnd":167.403,"pushStart":0,"pushEnd":0,"receiveHeadersEnd":197.102},"responseTime":1677428158330.246,"protocol":"h2","alternateProtocolUsage":"unspecifiedReason","securityState":"secure","securityDetails":{"protocol":"TLS 1.3","keyExchange":"","keyExchangeGroup":"X25519","cipher":"AES_128_GCM","certificateId":0,"subjectName":"sni.cloudflaressl.com","sanList":["datatables.net","*.datatables.net","sni.cloudflaressl.com"],"issuer":"Cloudflare Inc ECC CA-3","validFrom":1653696000,"validTo":1685318399,"signedCertificateTimestampList":[{"status":"Verified","origin":"Embedded in certificate","logDescription":"Google 'Xenon2023' log","logId":"ADF7BEFA7CFF10C88B9D3D9C1E3E186AB467295DCFB10C24CA858634EBDC828A","timestamp":1653702588059,"hashAlgorithm":"SHA-256","signatureAlgorithm":"ECDSA","signatureData":"30460221008A55E457978298E81C9EEA55768E3143D396559565BE638B7A1ADE0722B4416A022100FA744101E4AC45B8D4A3CA834AF9BEC4047E8D8816D51BCE297959DA55CE13CB"},{"status":"Verified","origin":"Embedded in certificate","logDescription":"DigiCert Yeti2023 Log","logId":"35CF191BBFB16C57BF0FAD4C6D42CBBBB627202651EA3FE12AEFA803C33BD64C","timestamp":1653702588020,"hashAlgorithm":"SHA-256","signatureAlgorithm":"ECDSA","signatureData":"3045022065B0396483E025C43DA4D5C0853F063A10AE86E72AEBC84ED73909C9701EC2BF022100AA5B9EA28ECC746B83697A8C26AA9F8D79EE04DCE1C4A74C21AC0362D3048894"},{"status":"Verified","origin":"Embedded in certificate","logDescription":"DigiCert Nessie2023 Log","logId":"B3737707E18450F86386D605A9DC11094A792DB1670C0B87DCF0030E7936A59A","timestamp":1653702588056,"hashAlgorithm":"SHA-256","signatureAlgorithm":"ECDSA","signatureData":"304402203FADD94F60E5060A766D686DF7EFCD4A89F15B8857CF0BFA5FD5430CABE8FD2B02200B134BF7EB64B66E4B593039780F04D133251E4C9C944E7E313A70D2AEF682FD"}],"certificateTransparencyCompliance":"unknown","serverSignatureAlgorithm":1027,"encryptedClientHello":false}},"hasExtraInfo":true,"frameId":"E238CD07DCE50A19F2D32BA4459B3546"},"sessionId":"B12D271AD6E9B7F564EC1EE94D1DB8A2"},
  {"method":"Network.dataReceived","params":{"requestId":"214053.3","timestamp":14027.281903,"dataLength":15984,"encodedDataLength":0},"sessionId":"B12D271AD6E9B7F564EC1EE94D1DB8A2"},
  {"method":"Network.dataReceived","params":{"requestId":"214053.3","timestamp":14027.283243,"dataLength":68663,"encodedDataLength":29074},"sessionId":"B12D271AD6E9B7F564EC1EE94D1DB8A2"},
  {"method":"Network.loadingFinished","params":{"requestId":"214053.3","timestamp":14027.283107,"encodedDataLength":29178,"shouldReportCorbBlocking":false},"sessionId":"B12D271AD6E9B7F564EC1EE94D1DB8A2"},
  {"method":"Page.loadEventFired","params":{"timestamp":14027.301793},"sessionId":"B12D271AD6E9B7F564EC1EE94D1DB8A2"},
  {"method":"Page.lifecycleEvent","params":{"frameId":"E238CD07DCE50A19F2D32BA4459B3546","loaderId":"00067A54E4D57474C9DD15E683E7B32C","name":"load","timestamp":14027.301793},"sessionId":"B12D271AD6E9B7F564EC1EE94D1DB8A2"},
  {"method":"Page.frameStoppedLoading","params":{"frameId":"E238CD07DCE50A19F2D32BA4459B3546"},"sessionId":"B12D271AD6E9B7F564EC1EE94D1DB8A2"},
  {"method":"Page.domContentEventFired","params":{"timestamp":14027.31581},"sessionId":"B12D271AD6E9B7F564EC1EE94D1DB8A2"},
  {"method":"Page.lifecycleEvent","params":{"frameId":"E238CD07DCE50A19F2D32BA4459B3546","loaderId":"00067A54E4D57474C9DD15E683E7B32C","name":"DOMContentLoaded","timestamp":14027.31581},"sessionId":"B12D271AD6E9B7F564EC1EE94D1DB8A2"},
  {"method":"Page.lifecycleEvent","params":{"frameId":"E238CD07DCE50A19F2D32BA4459B3546","loaderId":"00067A54E4D57474C9DD15E683E7B32C","name":"firstPaint","timestamp":14027.317058},"sessionId":"B12D271AD6E9B7F564EC1EE94D1DB8A2"},
  {"method":"Page.lifecycleEvent","params":{"frameId":"E238CD07DCE50A19F2D32BA4459B3546","loaderId":"00067A54E4D57474C9DD15E683E7B32C","name":"firstContentfulPaint","timestamp":14027.317142},"sessionId":"B12D271AD6E9B7F564EC1EE94D1DB8A2"},
  {"method":"Page.lifecycleEvent","params":{"frameId":"E238CD07DCE50A19F2D32BA4459B3546","loaderId":"00067A54E4D57474C9DD15E683E7B32C","name":"firstMeaningfulPaintCandidate","timestamp":14027.31727},"sessionId":"B12D271AD6E9B7F564EC1EE94D1DB8A2"},
  {"method":"Network.requestWillBeSentExtraInfo","params":{"requestId":"214053.12","associatedCookies":[],"headers":{":authority":"cdn.datatables.net",":method":"GET",":path":"/1.10.21/images/sort_both.png",":scheme":"https","accept":"image/avif,image/webp,image/apng,image/svg+xml,image/*,*/*;q=0.8","accept-encoding":"gzip, deflate, br","accept-language":"fr-FR,fr;q=0.9,en-US;q=0.8,en;q=0.7","referer":"https://cdn.datatables.net/1.10.21/css/jquery.dataTables.min.css","sec-ch-ua":"\"Chromium\";v=\"109\", \"Google Chrome\";v=\"109\", \"Lighthouse\";v=\"10.0.0\"","sec-ch-ua-mobile":"?1","sec-ch-ua-platform":"\"Android\"","sec-fetch-dest":"image","sec-fetch-mode":"no-cors","sec-fetch-site":"cross-site","user-agent":"Mozilla/5.0 (Linux; Android 11; moto g power (2022)) AppleWebKit/537.36 (KHTML, like Gecko) Chrome/109.0.0.0 Mobile Safari/537.36"},"connectTiming":{"requestTime":14027.361521},"clientSecurityState":{"initiatorIsSecureContext":true,"initiatorIPAddressSpace":"Local","privateNetworkRequestPolicy":"PreflightWarn"}},"sessionId":"B12D271AD6E9B7F564EC1EE94D1DB8A2"},
  {"method":"Network.requestWillBeSent","params":{"requestId":"214053.12","loaderId":"00067A54E4D57474C9DD15E683E7B32C","documentURL":"http://localhost:8081/employee-list.html","request":{"url":"https://cdn.datatables.net/1.10.21/images/sort_both.png","method":"GET","headers":{"sec-ch-ua":"\"Chromium\";v=\"109\", \"Google Chrome\";v=\"109\", \"Lighthouse\";v=\"10.0.0\"","Referer":"https://cdn.datatables.net/1.10.21/css/jquery.dataTables.min.css","sec-ch-ua-mobile":"?1","User-Agent":"Mozilla/5.0 (Linux; Android 11; moto g power (2022)) AppleWebKit/537.36 (KHTML, like Gecko) Chrome/109.0.0.0 Mobile Safari/537.36","sec-ch-ua-platform":"\"Android\""},"mixedContentType":"none","initialPriority":"Low","referrerPolicy":"strict-origin-when-cross-origin","isSameSite":false},"timestamp":14027.360905,"wallTime":1677428158.413744,"initiator":{"type":"parser","url":"https://cdn.datatables.net/1.10.21/css/jquery.dataTables.min.css"},"redirectHasExtraInfo":false,"type":"Image","frameId":"E238CD07DCE50A19F2D32BA4459B3546","hasUserGesture":false},"sessionId":"B12D271AD6E9B7F564EC1EE94D1DB8A2"},
  {"method":"Network.resourceChangedPriority","params":{"requestId":"214053.12","newPriority":"High","timestamp":14027.367322},"sessionId":"B12D271AD6E9B7F564EC1EE94D1DB8A2"},
  {"method":"Network.requestWillBeSentExtraInfo","params":{"requestId":"214053.13","associatedCookies":[],"headers":{":authority":"cdn.datatables.net",":method":"GET",":path":"/1.10.21/images/sort_asc.png",":scheme":"https","accept":"image/avif,image/webp,image/apng,image/svg+xml,image/*,*/*;q=0.8","accept-encoding":"gzip, deflate, br","accept-language":"fr-FR,fr;q=0.9,en-US;q=0.8,en;q=0.7","referer":"https://cdn.datatables.net/1.10.21/css/jquery.dataTables.min.css","sec-ch-ua":"\"Chromium\";v=\"109\", \"Google Chrome\";v=\"109\", \"Lighthouse\";v=\"10.0.0\"","sec-ch-ua-mobile":"?1","sec-ch-ua-platform":"\"Android\"","sec-fetch-dest":"image","sec-fetch-mode":"no-cors","sec-fetch-site":"cross-site","user-agent":"Mozilla/5.0 (Linux; Android 11; moto g power (2022)) AppleWebKit/537.36 (KHTML, like Gecko) Chrome/109.0.0.0 Mobile Safari/537.36"},"connectTiming":{"requestTime":14027.379174},"clientSecurityState":{"initiatorIsSecureContext":true,"initiatorIPAddressSpace":"Local","privateNetworkRequestPolicy":"PreflightWarn"}},"sessionId":"B12D271AD6E9B7F564EC1EE94D1DB8A2"},
  {"method":"Network.responseReceivedExtraInfo","params":{"requestId":"214053.12","blockedCookies":[],"headers":{"accept-ranges":"bytes","age":"2204830","cache-control":"max-age=31536000","cf-cache-status":"HIT","cf-ray":"79f9fb861b623a3e-FRA","content-length":"201","content-type":"image/png","date":"Sun, 26 Feb 2023 16:15:58 GMT","etag":"\"15e0096-c9-5ed32f45b6390\"","expires":"Thu, 01 Feb 2024 03:48:48 GMT","last-modified":"Fri, 11 Nov 2022 14:46:27 GMT","server":"cloudflare","vary":"Accept-Encoding","x-frame-options":"SAMEORIGIN"},"resourceIPAddressSpace":"Public","statusCode":200},"sessionId":"B12D271AD6E9B7F564EC1EE94D1DB8A2"},
  {"method":"Network.requestWillBeSent","params":{"requestId":"214053.13","loaderId":"00067A54E4D57474C9DD15E683E7B32C","documentURL":"http://localhost:8081/employee-list.html","request":{"url":"https://cdn.datatables.net/1.10.21/images/sort_asc.png","method":"GET","headers":{"sec-ch-ua":"\"Chromium\";v=\"109\", \"Google Chrome\";v=\"109\", \"Lighthouse\";v=\"10.0.0\"","Referer":"https://cdn.datatables.net/1.10.21/css/jquery.dataTables.min.css","sec-ch-ua-mobile":"?1","User-Agent":"Mozilla/5.0 (Linux; Android 11; moto g power (2022)) AppleWebKit/537.36 (KHTML, like Gecko) Chrome/109.0.0.0 Mobile Safari/537.36","sec-ch-ua-platform":"\"Android\""},"mixedContentType":"none","initialPriority":"Low","referrerPolicy":"strict-origin-when-cross-origin","isSameSite":false},"timestamp":14027.378678,"wallTime":1677428158.431525,"initiator":{"type":"parser","url":"https://cdn.datatables.net/1.10.21/css/jquery.dataTables.min.css"},"redirectHasExtraInfo":false,"type":"Image","frameId":"E238CD07DCE50A19F2D32BA4459B3546","hasUserGesture":false},"sessionId":"B12D271AD6E9B7F564EC1EE94D1DB8A2"},
  {"method":"Network.resourceChangedPriority","params":{"requestId":"214053.13","newPriority":"High","timestamp":14027.380029},"sessionId":"B12D271AD6E9B7F564EC1EE94D1DB8A2"},
  {"method":"Network.requestWillBeSent","params":{"requestId":"214053.14","loaderId":"00067A54E4D57474C9DD15E683E7B32C","documentURL":"http://localhost:8081/employee-list.html","request":{"url":"http://localhost:8081/favicon.ico","method":"GET","headers":{"sec-ch-ua":"\"Chromium\";v=\"109\", \"Google Chrome\";v=\"109\", \"Lighthouse\";v=\"10.0.0\"","Referer":"http://localhost:8081/employee-list.html","sec-ch-ua-mobile":"?1","User-Agent":"Mozilla/5.0 (Linux; Android 11; moto g power (2022)) AppleWebKit/537.36 (KHTML, like Gecko) Chrome/109.0.0.0 Mobile Safari/537.36","sec-ch-ua-platform":"\"Android\""},"mixedContentType":"none","initialPriority":"High","referrerPolicy":"strict-origin-when-cross-origin","isSameSite":true},"timestamp":14027.382411,"wallTime":1677428158.435312,"initiator":{"type":"other"},"redirectHasExtraInfo":false,"type":"Other","frameId":"E238CD07DCE50A19F2D32BA4459B3546","hasUserGesture":false},"sessionId":"B12D271AD6E9B7F564EC1EE94D1DB8A2"},
  {"method":"Network.responseReceived","params":{"requestId":"214053.12","loaderId":"00067A54E4D57474C9DD15E683E7B32C","timestamp":14027.383307,"type":"Image","response":{"url":"https://cdn.datatables.net/1.10.21/images/sort_both.png","status":200,"statusText":"","headers":{"date":"Sun, 26 Feb 2023 16:15:58 GMT","cf-cache-status":"HIT","last-modified":"Fri, 11 Nov 2022 14:46:27 GMT","server":"cloudflare","age":"2204830","etag":"\"15e0096-c9-5ed32f45b6390\"","x-frame-options":"SAMEORIGIN","vary":"Accept-Encoding","content-type":"image/png","cache-control":"max-age=31536000","accept-ranges":"bytes","cf-ray":"79f9fb861b623a3e-FRA","content-length":"201","expires":"Thu, 01 Feb 2024 03:48:48 GMT"},"mimeType":"image/png","connectionReused":true,"connectionId":84,"remoteIPAddress":"[2606:4700:10::6816:325d]","remotePort":443,"fromDiskCache":false,"fromServiceWorker":false,"fromPrefetchCache":false,"encodedDataLength":114,"timing":{"requestTime":14027.361521,"proxyStart":-1,"proxyEnd":-1,"dnsStart":-1,"dnsEnd":-1,"connectStart":-1,"connectEnd":-1,"sslStart":-1,"sslEnd":-1,"workerStart":-1,"workerReady":-1,"workerFetchStart":-1,"workerRespondWithSettled":-1,"sendStart":0.264,"sendEnd":0.472,"pushStart":0,"pushEnd":0,"receiveHeadersEnd":19.652},"responseTime":1677428158433.845,"protocol":"h2","alternateProtocolUsage":"unspecifiedReason","securityState":"secure","securityDetails":{"protocol":"TLS 1.3","keyExchange":"","keyExchangeGroup":"X25519","cipher":"AES_128_GCM","certificateId":0,"subjectName":"sni.cloudflaressl.com","sanList":["datatables.net","*.datatables.net","sni.cloudflaressl.com"],"issuer":"Cloudflare Inc ECC CA-3","validFrom":1653696000,"validTo":1685318399,"signedCertificateTimestampList":[{"status":"Verified","origin":"Embedded in certificate","logDescription":"Google 'Xenon2023' log","logId":"ADF7BEFA7CFF10C88B9D3D9C1E3E186AB467295DCFB10C24CA858634EBDC828A","timestamp":1653702588059,"hashAlgorithm":"SHA-256","signatureAlgorithm":"ECDSA","signatureData":"30460221008A55E457978298E81C9EEA55768E3143D396559565BE638B7A1ADE0722B4416A022100FA744101E4AC45B8D4A3CA834AF9BEC4047E8D8816D51BCE297959DA55CE13CB"},{"status":"Verified","origin":"Embedded in certificate","logDescription":"DigiCert Yeti2023 Log","logId":"35CF191BBFB16C57BF0FAD4C6D42CBBBB627202651EA3FE12AEFA803C33BD64C","timestamp":1653702588020,"hashAlgorithm":"SHA-256","signatureAlgorithm":"ECDSA","signatureData":"3045022065B0396483E025C43DA4D5C0853F063A10AE86E72AEBC84ED73909C9701EC2BF022100AA5B9EA28ECC746B83697A8C26AA9F8D79EE04DCE1C4A74C21AC0362D3048894"},{"status":"Verified","origin":"Embedded in certificate","logDescription":"DigiCert Nessie2023 Log","logId":"B3737707E18450F86386D605A9DC11094A792DB1670C0B87DCF0030E7936A59A","timestamp":1653702588056,"hashAlgorithm":"SHA-256","signatureAlgorithm":"ECDSA","signatureData":"304402203FADD94F60E5060A766D686DF7EFCD4A89F15B8857CF0BFA5FD5430CABE8FD2B02200B134BF7EB64B66E4B593039780F04D133251E4C9C944E7E313A70D2AEF682FD"}],"certificateTransparencyCompliance":"unknown","serverSignatureAlgorithm":1027,"encryptedClientHello":false}},"hasExtraInfo":true,"frameId":"E238CD07DCE50A19F2D32BA4459B3546"},"sessionId":"B12D271AD6E9B7F564EC1EE94D1DB8A2"},
  {"method":"Network.dataReceived","params":{"requestId":"214053.12","timestamp":14027.383859,"dataLength":201,"encodedDataLength":0},"sessionId":"B12D271AD6E9B7F564EC1EE94D1DB8A2"},
  {"method":"Network.loadingFinished","params":{"requestId":"214053.12","timestamp":14027.382877,"encodedDataLength":333,"shouldReportCorbBlocking":false},"sessionId":"B12D271AD6E9B7F564EC1EE94D1DB8A2"},
  {"method":"Network.requestWillBeSentExtraInfo","params":{"requestId":"214053.14","associatedCookies":[],"headers":{"Accept":"image/avif,image/webp,image/apng,image/svg+xml,image/*,*/*;q=0.8","Accept-Encoding":"gzip, deflate, br","Accept-Language":"fr-FR,fr;q=0.9,en-US;q=0.8,en;q=0.7","Connection":"keep-alive","Host":"localhost:8081","Referer":"http://localhost:8081/employee-list.html","Sec-Fetch-Dest":"image","Sec-Fetch-Mode":"no-cors","Sec-Fetch-Site":"same-origin","User-Agent":"Mozilla/5.0 (Linux; Android 11; moto g power (2022)) AppleWebKit/537.36 (KHTML, like Gecko) Chrome/109.0.0.0 Mobile Safari/537.36","sec-ch-ua":"\"Chromium\";v=\"109\", \"Google Chrome\";v=\"109\", \"Lighthouse\";v=\"10.0.0\"","sec-ch-ua-mobile":"?1","sec-ch-ua-platform":"\"Android\""},"connectTiming":{"requestTime":14027.383305},"clientSecurityState":{"initiatorIsSecureContext":true,"initiatorIPAddressSpace":"Local","privateNetworkRequestPolicy":"PreflightWarn"}},"sessionId":"B12D271AD6E9B7F564EC1EE94D1DB8A2"},
  {"method":"Network.responseReceivedExtraInfo","params":{"requestId":"214053.14","blockedCookies":[],"headers":{"Connection":"keep-alive","Content-Length":"0","Date":"Sun, 26 Feb 2023 16:15:58 GMT","Keep-Alive":"timeout=5","accept-ranges":"bytes"},"resourceIPAddressSpace":"Local","statusCode":404,"headersText":"HTTP/1.1 404 Not Found\r\naccept-ranges: bytes\r\nDate: Sun, 26 Feb 2023 16:15:58 GMT\r\nConnection: keep-alive\r\nKeep-Alive: timeout=5\r\nContent-Length: 0\r\n\r\n"},"sessionId":"B12D271AD6E9B7F564EC1EE94D1DB8A2"},
  {"method":"Network.responseReceived","params":{"requestId":"214053.14","loaderId":"00067A54E4D57474C9DD15E683E7B32C","timestamp":14027.388549,"type":"Other","response":{"url":"http://localhost:8081/favicon.ico","status":404,"statusText":"Not Found","headers":{"Date":"Sun, 26 Feb 2023 16:15:58 GMT","Connection":"keep-alive","accept-ranges":"bytes","Keep-Alive":"timeout=5","Content-Length":"0"},"mimeType":"text/plain","connectionReused":true,"connectionId":57,"remoteIPAddress":"127.0.0.1","remotePort":8081,"fromDiskCache":false,"fromServiceWorker":false,"fromPrefetchCache":false,"encodedDataLength":151,"timing":{"requestTime":14027.383305,"proxyStart":-1,"proxyEnd":-1,"dnsStart":-1,"dnsEnd":-1,"connectStart":-1,"connectEnd":-1,"sslStart":-1,"sslEnd":-1,"workerStart":-1,"workerReady":-1,"workerFetchStart":-1,"workerRespondWithSettled":-1,"sendStart":0.398,"sendEnd":0.482,"pushStart":0,"pushEnd":0,"receiveHeadersEnd":2.794},"responseTime":1677428158438.779,"protocol":"http/1.1","alternateProtocolUsage":"unspecifiedReason","securityState":"secure"},"hasExtraInfo":true,"frameId":"E238CD07DCE50A19F2D32BA4459B3546"},"sessionId":"B12D271AD6E9B7F564EC1EE94D1DB8A2"},
  {"method":"Network.loadingFinished","params":{"requestId":"214053.14","timestamp":14027.388217,"encodedDataLength":151,"shouldReportCorbBlocking":false},"sessionId":"B12D271AD6E9B7F564EC1EE94D1DB8A2"},
  {"method":"Network.responseReceivedExtraInfo","params":{"requestId":"214053.13","blockedCookies":[],"headers":{"accept-ranges":"bytes","age":"2205171","cache-control":"max-age=31536000","cf-cache-status":"HIT","cf-ray":"79f9fb863b8e3a3e-FRA","content-length":"160","content-type":"image/png","date":"Sun, 26 Feb 2023 16:15:58 GMT","etag":"\"15e0094-a0-5ed32f45b6390\"","expires":"Thu, 01 Feb 2024 03:43:07 GMT","last-modified":"Fri, 11 Nov 2022 14:46:27 GMT","server":"cloudflare","vary":"Accept-Encoding","x-frame-options":"SAMEORIGIN"},"resourceIPAddressSpace":"Public","statusCode":200},"sessionId":"B12D271AD6E9B7F564EC1EE94D1DB8A2"},
  {"method":"Network.responseReceived","params":{"requestId":"214053.13","loaderId":"00067A54E4D57474C9DD15E683E7B32C","timestamp":14027.40473,"type":"Image","response":{"url":"https://cdn.datatables.net/1.10.21/images/sort_asc.png","status":200,"statusText":"","headers":{"date":"Sun, 26 Feb 2023 16:15:58 GMT","cf-cache-status":"HIT","last-modified":"Fri, 11 Nov 2022 14:46:27 GMT","server":"cloudflare","age":"2205171","etag":"\"15e0094-a0-5ed32f45b6390\"","x-frame-options":"SAMEORIGIN","vary":"Accept-Encoding","content-type":"image/png","cache-control":"max-age=31536000","accept-ranges":"bytes","cf-ray":"79f9fb863b8e3a3e-FRA","content-length":"160","expires":"Thu, 01 Feb 2024 03:43:07 GMT"},"mimeType":"image/png","connectionReused":true,"connectionId":84,"remoteIPAddress":"[2606:4700:10::6816:325d]","remotePort":443,"fromDiskCache":false,"fromServiceWorker":false,"fromPrefetchCache":false,"encodedDataLength":94,"timing":{"requestTime":14027.379174,"proxyStart":-1,"proxyEnd":-1,"dnsStart":-1,"dnsEnd":-1,"connectStart":-1,"connectEnd":-1,"sslStart":-1,"sslEnd":-1,"workerStart":-1,"workerReady":-1,"workerFetchStart":-1,"workerRespondWithSettled":-1,"sendStart":0.287,"sendEnd":0.463,"pushStart":0,"pushEnd":0,"receiveHeadersEnd":23.596},"responseTime":1677428158455.432,"protocol":"h2","alternateProtocolUsage":"unspecifiedReason","securityState":"secure","securityDetails":{"protocol":"TLS 1.3","keyExchange":"","keyExchangeGroup":"X25519","cipher":"AES_128_GCM","certificateId":0,"subjectName":"sni.cloudflaressl.com","sanList":["datatables.net","*.datatables.net","sni.cloudflaressl.com"],"issuer":"Cloudflare Inc ECC CA-3","validFrom":1653696000,"validTo":1685318399,"signedCertificateTimestampList":[{"status":"Verified","origin":"Embedded in certificate","logDescription":"Google 'Xenon2023' log","logId":"ADF7BEFA7CFF10C88B9D3D9C1E3E186AB467295DCFB10C24CA858634EBDC828A","timestamp":1653702588059,"hashAlgorithm":"SHA-256","signatureAlgorithm":"ECDSA","signatureData":"30460221008A55E457978298E81C9EEA55768E3143D396559565BE638B7A1ADE0722B4416A022100FA744101E4AC45B8D4A3CA834AF9BEC4047E8D8816D51BCE297959DA55CE13CB"},{"status":"Verified","origin":"Embedded in certificate","logDescription":"DigiCert Yeti2023 Log","logId":"35CF191BBFB16C57BF0FAD4C6D42CBBBB627202651EA3FE12AEFA803C33BD64C","timestamp":1653702588020,"hashAlgorithm":"SHA-256","signatureAlgorithm":"ECDSA","signatureData":"3045022065B0396483E025C43DA4D5C0853F063A10AE86E72AEBC84ED73909C9701EC2BF022100AA5B9EA28ECC746B83697A8C26AA9F8D79EE04DCE1C4A74C21AC0362D3048894"},{"status":"Verified","origin":"Embedded in certificate","logDescription":"DigiCert Nessie2023 Log","logId":"B3737707E18450F86386D605A9DC11094A792DB1670C0B87DCF0030E7936A59A","timestamp":1653702588056,"hashAlgorithm":"SHA-256","signatureAlgorithm":"ECDSA","signatureData":"304402203FADD94F60E5060A766D686DF7EFCD4A89F15B8857CF0BFA5FD5430CABE8FD2B02200B134BF7EB64B66E4B593039780F04D133251E4C9C944E7E313A70D2AEF682FD"}],"certificateTransparencyCompliance":"unknown","serverSignatureAlgorithm":1027,"encryptedClientHello":false}},"hasExtraInfo":true,"frameId":"E238CD07DCE50A19F2D32BA4459B3546"},"sessionId":"B12D271AD6E9B7F564EC1EE94D1DB8A2"},
  {"method":"Network.dataReceived","params":{"requestId":"214053.13","timestamp":14027.404829,"dataLength":160,"encodedDataLength":0},"sessionId":"B12D271AD6E9B7F564EC1EE94D1DB8A2"},
  {"method":"Network.loadingFinished","params":{"requestId":"214053.13","timestamp":14027.404356,"encodedDataLength":272,"shouldReportCorbBlocking":false},"sessionId":"B12D271AD6E9B7F564EC1EE94D1DB8A2"},
  {"method":"Page.lifecycleEvent","params":{"frameId":"E238CD07DCE50A19F2D32BA4459B3546","loaderId":"00067A54E4D57474C9DD15E683E7B32C","name":"firstMeaningfulPaintCandidate","timestamp":14027.411162},"sessionId":"B12D271AD6E9B7F564EC1EE94D1DB8A2"},
  {"method":"Page.lifecycleEvent","params":{"frameId":"E238CD07DCE50A19F2D32BA4459B3546","loaderId":"00067A54E4D57474C9DD15E683E7B32C","name":"firstImagePaint","timestamp":14027.427895},"sessionId":"B12D271AD6E9B7F564EC1EE94D1DB8A2"},
  {"method":"Page.lifecycleEvent","params":{"frameId":"E238CD07DCE50A19F2D32BA4459B3546","loaderId":"00067A54E4D57474C9DD15E683E7B32C","name":"networkAlmostIdle","timestamp":14027.384429},"sessionId":"B12D271AD6E9B7F564EC1EE94D1DB8A2"},
  {"method":"Page.lifecycleEvent","params":{"frameId":"E238CD07DCE50A19F2D32BA4459B3546","loaderId":"00067A54E4D57474C9DD15E683E7B32C","name":"firstMeaningfulPaint","timestamp":14027.411162},"sessionId":"B12D271AD6E9B7F564EC1EE94D1DB8A2"},
  {"method":"Page.lifecycleEvent","params":{"frameId":"E238CD07DCE50A19F2D32BA4459B3546","loaderId":"00067A54E4D57474C9DD15E683E7B32C","name":"networkIdle","timestamp":14027.405393},"sessionId":"B12D271AD6E9B7F564EC1EE94D1DB8A2"},
  {"method":"Runtime.executionContextCreated","params":{"context":{"id":9,"origin":"","name":"lighthouse_isolated_context","uniqueId":"-2904671037387958850.4246271460995416205","auxData":{"isDefault":false,"type":"isolated","frameId":"E238CD07DCE50A19F2D32BA4459B3546"}}},"sessionId":"B12D271AD6E9B7F564EC1EE94D1DB8A2"}
]
